[
    {
        "manufacturer": "Sonoff",
        "model": "TRVZB",
        "img": "https://www.zigbee2mqtt.io/images/devices/TRVZB.png",
        "state": "supported",
        "slug": "sonoff-trvzb",
        "type": "trv"
    },
    {
        "manufacturer": "Eutronic",
        "title": "Eutronic Comet",
        "model": "CoZB_dha",
        "img": "https://www.zigbee2mqtt.io/images/devices/CoZB_dha.png",
        "state": "community",
        "slug": "over-climate-valve",
        "type": "trv"
    },
    {
        "manufacturer": "Eutronic",
        "model": "COZB0001",
        "img": "https://www.zigbee2mqtt.io/images/devices/COZB0001.png",
        "state": "community",
        "slug": "over-climate-valve",
        "type": "trv"
    },
    {
        "manufacturer": "Danfoss",
        "title": "Danfoss Ally",
        "model": "014G2461",
        "img": "https://www.zigbee2mqtt.io/images/devices/014G2461.png",
        "state": "partially",
        "slug": "over-climate",
        "type": "trv"
    },
    {
        "manufacturer": "NodOn",
        "model": "SIN-4-FP-20",
        "img": "https://www.zigbee2mqtt.io/images/devices/SIN-4-FP-20.png",
        "state": "supported",
        "slug": "over-switch",
        "type": "electric"
    },
    {
        "manufacturer": "heatzy",
        "model": "pilote",
        "img": "https://images.squarespace-cdn.com/content/v1/57d112cb9f7456d72f62cd0f/1937c67e-c931-40b9-a66c-ae0fea0a4d43/heatzy-pilote-co%CC%82te%CC%81.jpg",
        "state": "supported",
        "type": "electric",
        "slug": "over-switch"
    }
]